mux2.v
// module mux2(input a, b, sel,output y);
// assign y = sel ? b : a;
// endmodule


module mux2(input a, b, sel,output reg y);
always@(*) begin 
if (sel==1'b0)
 y=a;
 else 
 y=b;
end
endmodule

mux2_tb.v
`include "mux2.v"
module mux2_tb;
    reg a, b, sel;
    wire y;
mux2 uut(a, b, sel, y);
initial begin
$dumpfile("mux2_tb.vcd");  
$dumpvars(0, mux2_tb);  
        a = 0; b = 0; sel = 0; #10;
        $display("a=%b, b=%b, sel=%b => y=%b", a, b, sel, y);
        
        a = 0; b = 1; sel = 0; #10;
        $display("a=%b, b=%b, sel=%b => y=%b", a, b, sel, y);
        
        a = 1; b = 0; sel = 0; #10;
        $display("a=%b, b=%b, sel=%b => y=%b", a, b, sel, y);
        
        a = 1; b = 1; sel = 0; #10;
        $display("a=%b, b=%b, sel=%b => y=%b", a, b, sel, y);
        
        a = 0; b = 0; sel = 1; #10;
        $display("a=%b, b=%b, sel=%b => y=%b", a, b, sel, y);
        
        a = 0; b = 1; sel = 1; #10;
        $display("a=%b, b=%b, sel=%b => y=%b", a, b, sel, y);
        
        a = 1; b = 0; sel = 1; #10;
        $display("a=%b, b=%b, sel=%b => y=%b", a, b, sel, y);
        
        a = 1; b = 1; sel = 1; #10;
        $display("a=%b, b=%b, sel=%b => y=%b", a, b, sel, y);
        
        $finish;
    end
endmodule

mux2_tb.vcd
$date
	Wed Apr 30 11:29:45 2025
$end
$version
	Icarus Verilog
$end
$timescale
	1s
$end
$scope module mux2_tb $end
$var wire 1 ! y $end
$var reg 1 " a $end
$var reg 1 # b $end
$var reg 1 $ sel $end
$scope module uut $end
$var wire 1 % a $end
$var wire 1 & b $end
$var wire 1 ' sel $end
$var reg 1 ( y $end
$upscope $end
$upscope $end
$enddefinitions $end
#0
$dumpvars
0(
0'
0&
0%
0$
0#
0"
0!
$end
#10
1#
1&
#20
1(
1!
0#
0&
1"
1%
#30
1#
1&
#40
0(
0!
1$
1'
0#
0&
0"
0%
#50
1(
1!
1#
1&
#60
0(
0!
0#
0&
1"
1%
#70
1(
1!
1#
1&
