mux4.v
//data flow terinary operator
module mux4(input [3:0]a, input [1:0]s, output reg y);
always @ (*)
y=s[1] ? s[0]? a[3] : a[2] :s[0]? a[1]:a[0];
endmodule

// contineous assignments 

module mux4(input [3:0]a, input [1:0]s, output y);
assign y= (~ s[1] & ~ s[0] & a[0]) | (~ s[1] & s[0] & a[1] ) | (s[1]& ~s[0] & a[2]) | (s[1] & s[0] & a[3]);
endmodule

//behavioural if-else and case statements 

module mux4(input [3:0]a, input [1:0]s, output reg y);
always @(*) begin 
if (s==2'b00 )      y=a[0];
else if(s==2'b01)   y=a[1];
else if(s==2'b10)   y=a[2];
else                y=a[3];
end
endmodule


module mux4(input [3:0]a, input [1:0]s, output reg y);
always @(*) begin 
case (s)
2'b00: y=a[0];
2'b01: y=a[1];
2'b10: y=a[2];
2'b11: y=a[3];
endcase
end 
endmodule

mux4_tb.v
// `include "mux4.v"
// `timescale 1ns/1ps

// module mux4_tb;
//     reg [3:0] a;
//     reg [1:0] s;
//     wire y;
//  mux4 uut (a, s, y);
// initial begin
// $monitor(" s = %b%b, a = %b, y = %b", s[1], s[0], a, y);

// a = 4'b0000;
// s = 2'b00;
// #10 s = 2'b00;
// #10 s = 2'b01; 
// #10 s = 2'b10; 
// #10 s = 2'b11; 
// #10 a = 4'b1100;
// #10 s = 2'b00;
// #10 s = 2'b01; 
// #10 s = 2'b10; 
// #10 s = 2'b11; 

// #10 a = 4'b1111;
// #10 s = 2'b00;
// #10 s = 2'b01;
// #10 s = 2'b10;
// #10 s = 2'b11;

// #10 $finish;
// end

// initial begin
// $dumpfile("mux4_tb.vcd");
// $dumpvars(0, mux4_tb);
// end
// endmodule


///
`include "mux4.v"
`timescale 1ns/1ps

module mux4_tb;
    reg [3:0] a;
    reg [1:0] s;
    wire y;
mux4 uut (a, s, y);
initial begin
$monitor(" s = %b, a = %b, y = %b", s, a, y);
$dumpfile("mux4_tb.vcd");
$dumpvars(0, mux4_tb);

repeat (5) begin
a = $random;  
s = 2'b00; #10;
s = 2'b01; #10;
s = 2'b10; #10; 
s = 2'b11; #10; 

$display("Tested a = %b with all select lines", a);
end

a = 4'b0000; s = 2'b00; #10; 
a = 4'b1111; s = 2'b11; #10; 
a = 4'b0101; s = 2'b01; #10; 
a = 4'b1010; s = 2'b10; #10; 

$finish;
end
endmodule

mux4_tb.vcd
$date
	Wed May 07 06:16:22 2025
$end
$version
	Icarus Verilog
$end
$timescale
	1ps
$end
$scope module mux4_tb $end
$var wire 1 ! y $end
$var reg 4 " a [3:0] $end
$var reg 2 # s [1:0] $end
$scope module uut $end
$var wire 4 $ a [3:0] $end
$var wire 2 % s [1:0] $end
$var reg 1 & y $end
$upscope $end
$upscope $end
$enddefinitions $end
#0
$dumpvars
0&
b0 %
b100 $
b0 #
b100 "
0!
$end
#10000
b1 #
b1 %
#20000
1&
1!
b10 #
b10 %
#30000
0&
0!
b11 #
b11 %
#40000
1&
1!
b0 #
b0 %
b1 "
b1 $
#50000
0&
0!
b1 #
b1 %
#60000
b10 #
b10 %
#70000
b11 #
b11 %
#80000
1&
1!
b0 #
b0 %
b1001 "
b1001 $
#90000
0&
0!
b1 #
b1 %
#100000
b10 #
b10 %
#110000
1&
1!
b11 #
b11 %
#120000
b0 #
b0 %
b11 "
b11 $
#130000
b1 #
b1 %
#140000
0&
0!
b10 #
b10 %
#150000
b11 #
b11 %
#160000
1&
1!
b0 #
b0 %
b1101 "
b1101 $
#170000
0&
0!
b1 #
b1 %
#180000
1&
1!
b10 #
b10 %
#190000
b11 #
b11 %
#200000
0&
0!
b0 #
b0 %
b0 "
b0 $
#210000
1&
1!
b11 #
b11 %
b1111 "
b1111 $
#220000
0&
0!
b1 #
b1 %
b101 "
b101 $
#230000
b10 #
b10 %
b1010 "
b1010 $
